{"iid":"180l8u6","result":{"columns":["销量 8250","收藏1130人","默认快递"],"detailInfo":{"desc":"因为产品升级，清爽旅行套装和玫瑰旅行套装随机发货，敬请谅解！\n名称：御泥坊竹炭/绿豆泥浆套装\n功效：清爽控油，改善黑头毛孔，清洁祛痘\n主要成分：天然矿物泥浆，玉竹，七叶树籽\n产品明细：清爽三件套+清爽/玫瑰旅行套装+绿豆/竹炭泥浆+洗脸扑","detailImage":[{"anchor":"beauty_info","desc":"","key":"商品信息","list":["//s5.mogucdn.com/mlcdn/c45406/180504_0f5i0behc4f92fhg06gk2k264l3dk_640x910.jpg","//s11.mogucdn.com/mlcdn/c45406/180518_575lj7dj52hk65b5l22giekcdigil_640x400.jpg","//s11.mogucdn.com/mlcdn/c45406/180514_06k817e1f9iij1f5393clgbdb8855_640x812.jpg","//s5.mogucdn.com/mlcdn/c45406/180504_0a16iajf3ikl5k1e18103heablael_640x1460.jpg","//s11.mogucdn.com/mlcdn/c45406/180504_27e38cid4a37621ekf7715512k47d_640x1563.jpg","//s11.mogucdn.com/mlcdn/c45406/180504_0383f7893lke4hfhf0840k8g1cf0j_640x1634.jpg","//s11.mogucdn.com/mlcdn/c45406/180504_3e37l044fcig23l3a2k5dc9459718_640x1677.jpg","//s5.mogucdn.com/mlcdn/c45406/180504_13jec2iljj2ab1g59cj0hch6i93h1_640x612.jpg","//s11.mogucdn.com/mlcdn/c45406/180504_7edd397ibh6lh743c7l515c30f04l_640x1389.jpg","//s11.mogucdn.com/mlcdn/c45406/180504_0glgf5gkk7hghe8jeiccga4h2k13g_640x1286.jpg","//s11.mogucdn.com/p2/170317/77101615_86e9f0elcl86499l16jf26aallg14_1125x380.jpg"]},{"anchor":"brand_introduction","desc":"","key":"品牌介绍","list":["//s3.mogucdn.com/mlcdn/c45406/170531_8ad6ki476c44lhb6k8j4jl96jlj85_640x361.jpg","//s11.mogucdn.com/mlcdn/c45406/170410_89dgf4bb161jde654740jl40ghkja_640x875.jpg"]},{"anchor":"brand_authorization","desc":"","key":"品牌授权","list":["//s11.mogucdn.com/mlcdn/c45406/180119_7jhc9k0ih5if90c4gc9ffg0de4jc9_640x370.jpg"]},{"anchor":"beauty_service_info","desc":"","key":"服务说明","list":["//s11.mogucdn.com/p2/170320/84736276_4057k73db8e3a6jkhh5hgg33fdb02_640x985.jpg"]}],"video":{"cover":"//s11.mogucdn.com/mlcdn/c45406/170904_70897d3c380eil99e584729jh07hj_1920x1081.jpg","videoId":553495}},"esi":"<esi:try><esi:attempt><esi:include src='http://m.meilishuo.com/detail/mls/v1/h5_dyn?$(QUERY_STRING)'/></esi:attempt><esi:except></esi:except></esi:try>","isLogin":false,"itemInfo":{"addCartTips":false,"admin":false,"cFav":0,"cartNum":0,"cids":"#1160# #1635# #1247#","desc":"因为产品升级，清爽旅行套装和玫瑰旅行套装随机发货，敬请谅解！\n名称：御泥坊竹炭/绿豆泥浆套装\n功效：清爽控油，改善黑头毛孔，清洁祛痘\n主要成分：天然矿物泥浆，玉竹，七叶树籽\n产品明细：清爽三件套+清爽/玫瑰旅行套装+绿豆/竹炭泥浆+洗脸扑","discountBgColor":"#f13e3a","discountDesc":"优惠价","extra":{"deliveryTime":72,"sendAddress":""},"highNowPrice":"149.90","highPrice":"405.60","iid":"180l8u6","imUrl":"mls://imTalk?&source=1&goodsId=180l8u6&userId=12swdwg&shopId=14ty2","inActivity":false,"isFaved":false,"isGrayUser":false,"isNewComer":false,"isSelf":false,"lowNowPrice":"149.90","lowPrice":"405.60","oldPrice":"¥405.60","price":"¥149.90","redPacketsSwitch":false,"saleType":0,"shopId":"14ty2","state":0,"tags":"御泥坊,护肤品套装正品,控油祛痘套装,控油补水,化妆品套装","title":"【2件8折】御泥坊竹炭绿豆泥浆面膜护肤品套装化妆品官方正品控油祛痘补水保湿","topImages":["//s5.mogucdn.com/mlcdn/c45406/180507_637ejg9j795i3h6glc6a9dk4i1gf5_640x960.jpg","//s11.mogucdn.com/mlcdn/c45406/180501_05gcljecd4jd632j87027f33hajg2_640x960.jpg","//s11.mogucdn.com/mlcdn/c45406/180504_884b21932h3je0eaeac8i557gic81_640x960.jpg","//s11.mogucdn.com/mlcdn/c45406/180410_469698jl718d1410135jd7idjl5j5_640x960.jpg","//s11.mogucdn.com/mlcdn/c45406/180410_7jaaceh2e84i80012fd6b5gjd725g_640x960.jpg","//s11.mogucdn.com/mlcdn/c45406/180410_8ge9ja7ibja5i1g8ciebl1gf0dckc_640x960.jpg","//s11.mogucdn.com/mlcdn/c45406/180410_560bc580jleif9lc1l161f725k616_640x960.jpg"],"userId":"12swdwg","video":{"cover":"//s5.mogucdn.com/mlcdn/c45406/180507_206cfklg4gl5ea519ak3ih7ge602b_640x960.jpg","videoId":158699}},"itemParams":{"info":{"anchor":"product_info","key":"产品参数","set":[{"key":"产地","value":"广东省"},{"key":"厂名","value":"湖南御家化妆品制造有限公司"},{"key":"功效","value":"收缩毛孔,去黑头,毛孔隐形,控油,补水"},{"key":"国家","value":"中国内地"},{"key":"颜色","value":"绿豆控油祛痘套装,竹炭深层清洁套装"},{"key":"厂址","value":"长沙高新开发区青山路668号"},{"key":"保质期","value":"3年"},{"key":"成份／材质","value":"竹炭精粹"},{"key":"是否特殊化妆品","value":"否"},{"key":"适合肤质","value":"油性肤质,中性肤质,混合肤质"},{"key":"规格类型","value":"套装"},{"key":"是否进口","value":"否"}]}},"itemTags":[{"content":"严格审核，正规品牌授权链；精挑细选，国内外知名品牌合作。引领潮流趋势，时尚品质保证。","icon":"//s5.mogucdn.com/p1/160331/upload_ie4dcyjqgyytcm3bg4zdambqgiyde_30x31.png","name":"品牌认证"}],"promotions":{"alertData":{},"link":"mls://shoppro?shopId=14ty2","list":["满2件打8折"]},"rate":{"cRate":3223,"list":[{"canExplain":false,"content":"物流超级快，包装也特别好，客服小姐姐也超级棒！还送了两张面膜！喜欢喜欢喜欢！还有红包呦！","created":1537883481,"images":["//s11.mogucdn.com/mlcdn/c45406/180925_5i5hij0l77j33f8h4gi8gdl6j1eh6_576x1024.jpg","//s11.mogucdn.com/mlcdn/c45406/180925_1hg6b1jgd5c48f95gjgelghfgfaib_720x540.jpg","//s11.mogucdn.com/mlcdn/c45406/180925_45i2766g347231g9afedka3b2kk80_720x540.jpg"],"isAnonymous":1,"isEmpty":0,"level":"","rateId":"116cfmjm","style":"颜色:绿豆控油祛痘套装 ","user":{"avatar":"//s11.mogucdn.com/p2/161214/103488673_0l1ff9kf2hbc32fe4a2g05l77d89d_140x140.png","profileUrl":"","tagIndex":"","uid":"","uname":"小蘑菇6小Y"}}]},"shopInfo":{"allGoodsUrl":"http://m.meilishuo.com/shop/index/14ty2","cFans":904984,"cGoods":107,"cSells":1951773,"categories":[{"link":"http://s.meilishuo.com/14ty2/list/index?categoryId=1319321","name":"热销爆款"},{"link":"http://s.meilishuo.com/14ty2/list/index?categoryId=1494487","name":"超值套装"},{"link":"http://s.meilishuo.com/14ty2/list/index?categoryId=1494509","name":"男士护肤"},{"link":"http://s.meilishuo.com/14ty2/list/index?categoryId=1511724","name":"面贴专区"},{"link":"http://s.meilishuo.com/14ty2/list/index?categoryId=20061893","name":"周边护理"},{"link":"http://s.meilishuo.com/14ty2/list/index?categoryId=20107619","name":"所有面膜"},{"link":"http://s.meilishuo.com/14ty2/list/index?categoryId=20143551","name":"功效分类"},{"link":"http://s.meilishuo.com/14ty2/list/index?categoryId=20143552","name":"美白淡斑"},{"link":"http://s.meilishuo.com/14ty2/list/index?categoryId=20143554","name":"补水保湿"},{"link":"http://s.meilishuo.com/14ty2/list/index?categoryId=20143557","name":"清爽净透"},{"link":"http://s.meilishuo.com/14ty2/list/index?categoryId=20143558","name":"清洁祛痘"},{"link":"http://s.meilishuo.com/14ty2/list/index?categoryId=20143560","name":"紧致弹润"},{"link":"http://s.meilishuo.com/14ty2/list/index?categoryId=20201100","name":"泥浆"},{"link":"http://s.meilishuo.com/14ty2/list/index?categoryId=20201101","name":"单品"},{"link":"http://s.meilishuo.com/14ty2/list/index?categoryId=20201104","name":"舒缓修护"},{"link":"http://s.meilishuo.com/14ty2/list/index?categoryId=20234658","name":"高端系列"},{"link":"http://s.meilishuo.com/14ty2/list/index?categoryId=20234659","name":"睡眠"},{"link":"http://s.meilishuo.com/14ty2/list/index?categoryId=20292615","name":"潮流彩妆"},{"link":"http://s.meilishuo.com/14ty2/list/index?categoryId=20334576","name":"99元3件"},{"link":"http://s.meilishuo.com/14ty2/list/index?categoryId=20338995","name":"任意2件8折"},{"link":"http://s.meilishuo.com/14ty2/list/index?categoryId=20344308","name":"爆款买一送一"}],"isMarked":false,"level":5,"name":"御泥坊旗舰店","nonsupportReasonRefound":false,"score":[{"isBetter":true,"name":"描述相符","score":4.85},{"isBetter":true,"name":"价格合理","score":5},{"isBetter":true,"name":"质量满意","score":4.84}],"services":[{"icon":"//s11.mogucdn.com/p1/160607/upload_ie4tkmbtgqztomjqhezdambqgqyde_44x44.png","name":"48小时发货"},{"icon":"//s11.mogucdn.com/p1/160607/upload_ie4tkmbtgqztomjqhezdambqgqyde_44x44.png","name":"7天无理由退货"},{"icon":"//s11.mogucdn.com/p1/160607/upload_ie4tkmbtgqztomjqhezdambqgqyde_44x44.png","name":"退货补运费"}],"shopId":"14ty2","shopLogo":"//s3.mogucdn.com/mlcdn/c45406/170516_7a9c3fcga20el3k99h726j228cih6_320x320.jpg","shopUrl":"http://m.meilishuo.com/shop/index/14ty2","type":1,"userId":"12swdwg"},"skuInfo":{"defaultPrice":"¥149.90","isAbroad":false,"priceRange":"¥149.90","props":[{"isDefault":false,"label":"款式","list":[{"index":1,"isDefault":false,"name":"绿豆控油祛痘套装","styleId":1,"type":"style"},{"index":2,"isDefault":false,"name":"竹炭深层清洁套装","styleId":2,"type":"style"}]},{"isDefault":false,"label":"尺码","list":[{"index":100,"isDefault":false,"name":"均码","sizeId":100,"type":"size"}]}],"sizeKey":"尺码","skus":[{"currency":"￥","img":"//s5.mogucdn.com/mlcdn/c45406/180504_19420e81bd1ghce3539g0dc6eb57d_640x960.jpg","nowprice":14990,"price":40560,"size":"均码","sizeId":100,"stock":444,"stockId":"113k9cfo","style":"绿豆控油祛痘套装","styleId":1,"xdSkuId":"113k9cfo"},{"currency":"￥","img":"//s3.mogucdn.com/mlcdn/c45406/180504_6djkg41h6ke1gjbjf9469a9d55805_640x960.jpg","nowprice":14990,"price":40560,"size":"均码","sizeId":100,"stock":415,"stockId":"113k9cfq","style":"竹炭深层清洁套装","styleId":2,"xdSkuId":"113k9cfq"}],"styleKey":"款式","title":"【2件8折】御泥坊竹炭绿豆泥浆面膜护肤品套装化妆品官方正品控油祛痘补水保湿","totalStock":859},"topBar":{"img":"//s11.mogucdn.com/p1/150811/upload_ieytsmbrmm4wkm3ggizdambqmeyde_226x43.png","link":"http://www.xiaodian.com/h5/download"}},"status":{"code":1001,"msg":""}}