{"iid":"1kfaipy","result":{"columns":["销量 102","收藏3人","默认快递"],"detailInfo":{"desc":"正版粉红豹公仔粉红顽皮豹毛绒玩具可爱达浪布娃娃抱枕跳跳虎玩偶","detailImage":[{"anchor":"model_img","desc":"","key":"穿着效果","list":["//s11.mogucdn.com/mlcdn/c45406/170711_0cjl9l8chk4d839ebj85cii30g397_750x489.jpg","//s11.mogucdn.com/p2/170317/77101615_86e9f0elcl86499l16jf26aallg14_1125x380.jpg"]},{"anchor":"baipai_img2","desc":"","key":"整体款式","list":["//s11.mogucdn.com/mlcdn/c45406/170711_89igg9ejcejleale2ebleaj2bdf5g_750x715.jpg","//s3.mogucdn.com/mlcdn/c45406/170711_7l0c0l0cke73lee9aic3i70j26483_750x675.jpg","//s11.mogucdn.com/mlcdn/c45406/170711_43d7dafi77cj919e9fdcieb5ff6f6_750x560.jpg","//s3.mogucdn.com/mlcdn/c45406/170711_5dijkg7g40ceid18c1kdg04k0c3e0_750x792.jpg","//s11.mogucdn.com/mlcdn/c45406/170711_5g78dhjg60g981hlee6ka9a8ek8gl_750x735.jpg"]},{"anchor":"detail_img","desc":"","key":"细节做工","list":["//s11.mogucdn.com/mlcdn/c45406/170711_313e5f4iige5f881kfi93693kd1dh_750x502.jpg","//s11.mogucdn.com/mlcdn/c45406/170711_183b084jbebcl85biajl0l03d3i4j_750x553.jpg","//s3.mogucdn.com/mlcdn/c45406/170711_6bei4f4h2jf81425h6475ekfe55jg_750x560.jpg"]}]},"esi":"<esi:try><esi:attempt><esi:include src='http://m.meilishuo.com/detail/mls/v1/h5_dyn?$(QUERY_STRING)'/></esi:attempt><esi:except></esi:except></esi:try>","isLogin":false,"itemInfo":{"addCartTips":false,"admin":false,"cFav":0,"cartNum":0,"cids":"#3856# #4135# #1010#","desc":"正版粉红豹公仔粉红顽皮豹毛绒玩具可爱达浪布娃娃抱枕跳跳虎玩偶","discountBgColor":"#f13e3a","discountDesc":"7折","extra":{"deliveryTime":72,"sendAddress":""},"highNowPrice":"203.00","highPrice":"290.00","iid":"1kfaipy","imUrl":"mls://imTalk?&source=1&goodsId=1kfaipy&userId=1u6fuw&shopId=1id74","inActivity":false,"isFaved":false,"isGrayUser":false,"isNewComer":false,"isSelf":false,"lowNowPrice":"33.60","lowPrice":"48.00","oldPrice":"¥48.00","price":"¥33.60~¥203.00","redPacketsSwitch":false,"saleType":0,"shopId":"1id74","state":0,"tags":"","title":"正版粉红豹公仔粉红顽皮豹毛绒玩具可爱达浪布娃娃抱枕跳跳虎玩偶","topImages":["//s11.mogucdn.com/mlcdn/c45406/170711_29e88j33d3d9ljf58hd1gg6k5kkd7_1000x1500.jpg","//s11.mogucdn.com/mlcdn/c45406/170711_280f57l65c4cl9d182ih2jid22k5a_1000x1500.jpg","//s5.mogucdn.com/mlcdn/c45406/170711_077ae60kgi695jcgl16688bjagaf7_1000x1500.jpg","//s11.mogucdn.com/mlcdn/c45406/170711_725171hg252f1chbf7adfj2jk6739_1000x1500.jpg"],"userId":"1u6fuw"},"itemParams":{"info":{"anchor":"product_info","key":"产品参数","set":[{"key":"颜色","value":"粉色穿衣"},{"key":"尺寸","value":"80厘米（小孩玩耍）,1.5米（女神最爱）,1.3米（生日礼物）,1.1米（舒适抱枕）,1.8米（送礼超有面）,55厘米（小孩玩耍）"}]},"rule":{"anchor":"size_info","desc":"测量宝贝的最长度","disclaimer":"※ 以上尺寸为实物人工测量，因测量当时不同会有1-2cm误差，相关数据仅作参考，以收到实物为准。","key":"尺码说明","tables":[[["尺码","55厘米（小孩玩耍）","1.1米（舒适抱枕）","80厘米（小孩玩耍）","1.3米（生日礼物）"],["克重","0.5","1.1","0.9","1.5"]],[["尺码","1.5米（女神最爱）","1.8米（送礼超有面）"],["克重","1.8","2"]]]}},"promotions":{"alertData":{},"link":"mls://shoppro?shopId=1id74","list":["满100元减3元","满150元减5元","满200元减10元","满300元减20元"]},"rate":{"cRate":191,"list":[{"canExplain":false,"content":"萌萌哒可爱，爱不释手，不掉毛不褪色，价格比实体店便宜，物流快，质量好的很","created":1531993159,"isAnonymous":1,"isEmpty":0,"level":"","rateId":"115mdb3u","style":"颜色:粉色穿衣 尺寸:55厘米（小孩玩耍） ","user":{"avatar":"//s3.mogucdn.com/p2/161214/103488673_825c06kdj394515kkkjhhi0el8j86_140x141.png","profileUrl":"","tagIndex":"","uid":"","uname":"zYY小英202018"}}]},"shopInfo":{"allGoodsUrl":"http://m.meilishuo.com/shop/index/1id74","cFans":3210,"cGoods":178,"cSells":25119,"categories":[{"link":"http://s.meilishuo.com/1id74/list/index?categoryId=80680","name":"春季新款"},{"link":"http://s.meilishuo.com/1id74/list/index?categoryId=1466555","name":"公仔"},{"link":"http://s.meilishuo.com/1id74/list/index?categoryId=20051851","name":"潮流女包"}],"isMarked":false,"level":2,"name":"伊美玩具","nonsupportReasonRefound":false,"score":[{"isBetter":true,"name":"描述相符","score":4.83},{"isBetter":true,"name":"价格合理","score":5},{"isBetter":true,"name":"质量满意","score":4.78}],"services":[{"icon":"//s11.mogucdn.com/p1/160607/upload_ie4tkmbtgqztomjqhezdambqgqyde_44x44.png","name":"退货补运费"},{"icon":"//s11.mogucdn.com/p1/160607/upload_ie4tkmbtgqztomjqhezdambqgqyde_44x44.png","name":"全国包邮"},{"icon":"//s11.mogucdn.com/p1/160607/upload_ie4tkmbtgqztomjqhezdambqgqyde_44x44.png","name":"7天无理由退货"},{"icon":"//s11.mogucdn.com/p1/160607/upload_ie4tkmbtgqztomjqhezdambqgqyde_44x44.png","name":"72小时发货"}],"shopId":"1id74","shopLogo":"//s5.mogucdn.com/b7/avatar/150304/f37wo_ieztsmjsga2teylcmyytambqgyyde_200x200.jpg","shopUrl":"http://m.meilishuo.com/shop/index/1id74","type":1,"userId":"1u6fuw"},"skuInfo":{"defaultPrice":"¥33.60~¥203.00","isAbroad":false,"priceRange":"¥33.60~¥203.00","props":[{"isDefault":false,"label":"颜色:","list":[{"index":1,"isDefault":false,"name":"粉色穿衣","styleId":1,"type":"style"}]},{"isDefault":false,"label":"尺寸:","list":[{"index":100,"isDefault":false,"name":"55厘米（小孩玩耍）","sizeId":100,"type":"size"},{"index":101,"isDefault":false,"name":"1.1米（舒适抱枕）","sizeId":101,"type":"size"},{"index":102,"isDefault":false,"name":"80厘米（小孩玩耍）","sizeId":102,"type":"size"},{"index":103,"isDefault":false,"name":"1.3米（生日礼物）","sizeId":103,"type":"size"},{"index":104,"isDefault":false,"name":"1.5米（女神最爱）","sizeId":104,"type":"size"},{"index":105,"isDefault":false,"name":"1.8米（送礼超有面）","sizeId":105,"type":"size"}]}],"sizeKey":"尺寸","skus":[{"currency":"￥","img":"//s11.mogucdn.com/mlcdn/c45406/170711_4bldcka83b27fj27bf97c85ei9bl7_1000x1500.jpg","nowprice":3360,"price":4800,"size":"55厘米（小孩玩耍）","sizeId":100,"stock":867,"stockId":"1sik7kk","style":"粉色穿衣","styleId":1,"xdSkuId":"1sik7kk"},{"currency":"￥","img":"//s11.mogucdn.com/mlcdn/c45406/170711_4bldcka83b27fj27bf97c85ei9bl7_1000x1500.jpg","nowprice":7840,"price":11200,"size":"1.1米（舒适抱枕）","sizeId":101,"stock":951,"stockId":"1sik7km","style":"粉色穿衣","styleId":1,"xdSkuId":"1sik7km"},{"currency":"￥","img":"//s11.mogucdn.com/mlcdn/c45406/170711_4bldcka83b27fj27bf97c85ei9bl7_1000x1500.jpg","nowprice":4760,"price":6800,"size":"80厘米（小孩玩耍）","sizeId":102,"stock":918,"stockId":"1sik7ko","style":"粉色穿衣","styleId":1,"xdSkuId":"1sik7ko"},{"currency":"￥","img":"//s11.mogucdn.com/mlcdn/c45406/170711_4bldcka83b27fj27bf97c85ei9bl7_1000x1500.jpg","nowprice":11690,"price":16700,"size":"1.3米（生日礼物）","sizeId":103,"stock":968,"stockId":"1sik7kq","style":"粉色穿衣","styleId":1,"xdSkuId":"1sik7kq"},{"currency":"￥","img":"//s11.mogucdn.com/mlcdn/c45406/170711_4bldcka83b27fj27bf97c85ei9bl7_1000x1500.jpg","nowprice":15260,"price":21800,"size":"1.5米（女神最爱）","sizeId":104,"stock":979,"stockId":"1sik7ks","style":"粉色穿衣","styleId":1,"xdSkuId":"1sik7ks"},{"currency":"￥","img":"//s11.mogucdn.com/mlcdn/c45406/170711_4bldcka83b27fj27bf97c85ei9bl7_1000x1500.jpg","nowprice":20300,"price":29000,"size":"1.8米（送礼超有面）","sizeId":105,"stock":985,"stockId":"1sik7ku","style":"粉色穿衣","styleId":1,"xdSkuId":"1sik7ku"}],"styleKey":"颜色","title":"正版粉红豹公仔粉红顽皮豹毛绒玩具可爱达浪布娃娃抱枕跳跳虎玩偶","totalStock":5668},"topBar":{"img":"//s11.mogucdn.com/p1/150811/upload_ieytsmbrmm4wkm3ggizdambqmeyde_226x43.png","link":"http://www.xiaodian.com/h5/download"}},"status":{"code":1001,"msg":""}}