{"iid":"1m6ti9g","result":{"columns":["销量 216","收藏1人","默认快递"],"detailInfo":{"desc":"可乐定制易拉罐diy抖音热门同款生日礼物男女生毕业可口可乐礼盒","detailImage":[{"anchor":"model_img","desc":"","key":"穿着效果","list":["//s11.mogucdn.com/mlcdn/c45406/180803_6gc2i10jaidbbaid4i1i1db6h47gd_750x797.jpg","//s11.mogucdn.com/mlcdn/c45406/180803_684412b3a295dji4e54221k1di36l_750x796.jpg","//s11.mogucdn.com/mlcdn/c45406/180803_3k8i9bkj233g62i85h52d22ecf57h_750x797.jpg","//s5.mogucdn.com/mlcdn/c45406/180803_53e7f06d2fd15b35bj7a75k0ic87c_750x796.jpg","//s11.mogucdn.com/mlcdn/c45406/180803_26hfg97h209j9ddff4eij388agdle_750x797.jpg","//s11.mogucdn.com/mlcdn/c45406/180803_78cgdalj567bhlei0b6eh1d4kb71l_750x797.jpg","//s11.mogucdn.com/mlcdn/c45406/180803_60fl3ahbkf2757dl8jk53c8h5c601_750x796.jpg","//s11.mogucdn.com/mlcdn/c45406/180803_1h38h6ae7j7flfb55dh819iif8ab7_750x797.jpg","//s11.mogucdn.com/mlcdn/c45406/180803_1eijdakae1d7j9369bhebcigb5gb5_750x796.jpg","//s3.mogucdn.com/mlcdn/c45406/180803_68k57l6badecjk3il8lbjie4ii7i0_750x797.jpg","//s11.mogucdn.com/p2/170317/77101615_86e9f0elcl86499l16jf26aallg14_1125x380.jpg"]}]},"esi":"<esi:try><esi:attempt><esi:include src='http://m.meilishuo.com/detail/mls/v1/h5_dyn?$(QUERY_STRING)'/></esi:attempt><esi:except></esi:except></esi:try>","isLogin":false,"itemInfo":{"addCartTips":false,"admin":false,"cFav":0,"cartNum":0,"cids":"#3856# #2065# #2253# #3315#","desc":"可乐定制易拉罐diy抖音热门同款生日礼物男女生毕业可口可乐礼盒","discountBgColor":"#f13e3a","discountDesc":"店铺促销","extra":{"deliveryTime":72,"sendAddress":"江苏省宿迁市"},"highNowPrice":"59.00","highPrice":"84.29","iid":"1m6ti9g","imUrl":"mls://imTalk?&source=1&goodsId=1m6ti9g&userId=158f4jq&shopId=1170z7b8","inActivity":false,"isFaved":false,"isGrayUser":false,"isNewComer":false,"isSelf":false,"lowNowPrice":"13.80","lowPrice":"19.72","oldPrice":"¥19.72","price":"¥13.80~¥59.00","redPacketsSwitch":false,"saleType":0,"shopId":"1170z7b8","state":0,"tags":"","title":"可乐定制易拉罐diy抖音热门同款生日礼物男女生毕业可口可乐礼盒","topImages":["//s5.mogucdn.com/mlcdn/c45406/180803_87kae5kc1e5j8c375aafdik5k08d6_640x960.jpg","//s11.mogucdn.com/mlcdn/c45406/180803_6j6gl2183ckb1da7f73j3dbdiiea0_800x800.jpg","//s5.mogucdn.com/mlcdn/c45406/180803_8a2eia4fb11l37ii05550jea5k568_800x800.jpg","//s11.mogucdn.com/mlcdn/c45406/180803_291dg5li8edbe9jd09hii25672k6a_800x800.jpg","//s11.mogucdn.com/mlcdn/c45406/180803_762egfkdib64i5ej06a0akecaldgh_795x798.jpg"],"userId":"158f4jq"},"itemParams":{"info":{"anchor":"product_info","key":"产品参数","set":[{"key":"颜色","value":"百事可乐定制1罐+浅紫色玫瑰礼盒,可口可乐定制1罐+红玫瑰礼盒,百事可乐定制1罐+蓝玫瑰礼盒,百事+可口+红玫瑰礼盒,百事可乐定制1罐,可口可乐定制1罐+大红玫瑰礼盒,可口可乐定制1罐,可口可乐定制1罐+蓝玫瑰礼盒,百事可乐定制1罐+大红玫瑰礼盒,百事+可口+蓝玫瑰礼盒,百事可乐定制1罐+粉玫瑰礼盒,百事+可口+大红玫瑰礼盒,百事+可口+粉玫瑰礼盒,百事+可口+浅紫色玫瑰礼盒,百事可乐定制1罐+红玫瑰礼盒,可口可乐定制1罐+粉玫瑰礼盒,可口可乐定制1罐+浅紫色玫瑰礼盒"},{"key":"厂址","value":"江苏省宿迁市沭阳县苏奥软件园n5401"},{"key":"厂名","value":"宿迁林思书电子商务有限公司"}]}},"promotions":{"alertData":{},"link":"mls://shoppro?shopId=1170z7b8","list":["满30元减1元","满100元减5元"]},"rate":{"cRate":83,"list":[{"canExplain":false,"content":"宝贝包装很好 没有瑕疵 价格比别家便宜 很好很好 很好看阿 喜欢喜欢送朋友的生日礼物","created":1535545622,"isAnonymous":1,"isEmpty":0,"level":"","rateId":"1161h1sw","style":"颜色:百事可乐定制1罐+粉玫瑰礼盒 ","user":{"avatar":"//s5.mogucdn.com/p2/161214/103488673_8da6lhkf9a5h32ei6bd297523c35d_140x140.png","profileUrl":"","tagIndex":"","uid":"","uname":"李雪雪Vita"}}]},"shopInfo":{"allGoodsUrl":"http://m.meilishuo.com/shop/index/1170z7b8","cFans":10458,"cGoods":397,"cSells":227864,"categories":[{"link":"http://s.meilishuo.com/1170z7b8/list/index?categoryId=20079278","name":"家居饰品"},{"link":"http://s.meilishuo.com/1170z7b8/list/index?categoryId=20079279","name":"创意礼品"},{"link":"http://s.meilishuo.com/1170z7b8/list/index?categoryId=20079281","name":"文化书籍"},{"link":"http://s.meilishuo.com/1170z7b8/list/index?categoryId=20079282","name":"镇店之宝"},{"link":"http://s.meilishuo.com/1170z7b8/list/index?categoryId=20079284","name":"绿植盆栽专区"},{"link":"http://s.meilishuo.com/1170z7b8/list/index?categoryId=20079286","name":"开学必备"},{"link":"http://s.meilishuo.com/1170z7b8/list/index?categoryId=20079613","name":"宿舍必备"},{"link":"http://s.meilishuo.com/1170z7b8/list/index?categoryId=20080832","name":"女神必备"},{"link":"http://s.meilishuo.com/1170z7b8/list/index?categoryId=20081556","name":"男神必备"},{"link":"http://s.meilishuo.com/1170z7b8/list/index?categoryId=20081581","name":"男神必备"},{"link":"http://s.meilishuo.com/1170z7b8/list/index?categoryId=20083257","name":"宠物专区"},{"link":"http://s.meilishuo.com/1170z7b8/list/index?categoryId=20083902","name":"成人用品专区"},{"link":"http://s.meilishuo.com/1170z7b8/list/index?categoryId=20085116","name":"儿童专区"},{"link":"http://s.meilishuo.com/1170z7b8/list/index?categoryId=20086634","name":"日用百货"},{"link":"http://s.meilishuo.com/1170z7b8/list/index?categoryId=20088910","name":"办公用品"},{"link":"http://s.meilishuo.com/1170z7b8/list/index?categoryId=20091207","name":"节日专卖"},{"link":"http://s.meilishuo.com/1170z7b8/list/index?categoryId=20097041","name":"运动达人"},{"link":"http://s.meilishuo.com/1170z7b8/list/index?categoryId=20097042","name":"运动达人"},{"link":"http://s.meilishuo.com/1170z7b8/list/index?categoryId=20115917","name":"早教必备"}],"isMarked":false,"level":3,"name":"新巢家居馆","nonsupportReasonRefound":false,"score":[{"isBetter":false,"name":"描述相符","score":4.67},{"isBetter":true,"name":"价格合理","score":5},{"isBetter":false,"name":"质量满意","score":4.66}],"services":[{"icon":"//s11.mogucdn.com/p1/160607/upload_ie4tkmbtgqztomjqhezdambqgqyde_44x44.png","name":"7天无理由退货"},{"icon":"//s11.mogucdn.com/p1/160607/upload_ie4tkmbtgqztomjqhezdambqgqyde_44x44.png","name":"72小时发货"},{"icon":"//s11.mogucdn.com/p1/160607/upload_ie4tkmbtgqztomjqhezdambqgqyde_44x44.png","name":"退货补运费"}],"shopId":"1170z7b8","shopLogo":"//s11.mogucdn.com/p2/160819/upload_6a2f60d4dfi5h7ffdai2elic3g11a_500x500.jpg","shopUrl":"http://m.meilishuo.com/shop/index/1170z7b8","type":1,"userId":"158f4jq"},"skuInfo":{"defaultPrice":"¥13.80~¥59.00","isAbroad":false,"priceRange":"¥13.80~¥59.00","props":[{"isDefault":false,"label":"款式","list":[{"index":1,"isDefault":false,"name":"可口可乐定制1罐","styleId":1,"type":"style"},{"index":2,"isDefault":false,"name":"百事可乐定制1罐","styleId":2,"type":"style"},{"index":3,"isDefault":false,"name":"可口可乐定制1罐+红玫瑰礼盒","styleId":3,"type":"style"},{"index":4,"isDefault":false,"name":"可口可乐定制1罐+蓝玫瑰礼盒","styleId":4,"type":"style"},{"index":5,"isDefault":false,"name":"可口可乐定制1罐+粉玫瑰礼盒","styleId":5,"type":"style"},{"index":6,"isDefault":false,"name":"可口可乐定制1罐+浅紫色玫瑰礼盒","styleId":6,"type":"style"},{"index":7,"isDefault":false,"name":"可口可乐定制1罐+大红玫瑰礼盒","styleId":7,"type":"style"},{"index":8,"isDefault":false,"name":"百事可乐定制1罐+红玫瑰礼盒","styleId":8,"type":"style"},{"index":9,"isDefault":false,"name":"百事可乐定制1罐+蓝玫瑰礼盒","styleId":9,"type":"style"},{"index":10,"isDefault":false,"name":"百事可乐定制1罐+粉玫瑰礼盒","styleId":10,"type":"style"},{"index":11,"isDefault":false,"name":"百事可乐定制1罐+浅紫色玫瑰礼盒","styleId":11,"type":"style"},{"index":12,"isDefault":false,"name":"百事可乐定制1罐+大红玫瑰礼盒","styleId":12,"type":"style"},{"index":13,"isDefault":false,"name":"百事+可口+蓝玫瑰礼盒","styleId":13,"type":"style"},{"index":14,"isDefault":false,"name":"百事+可口+浅紫色玫瑰礼盒","styleId":14,"type":"style"},{"index":15,"isDefault":false,"name":"百事+可口+粉玫瑰礼盒","styleId":15,"type":"style"},{"index":16,"isDefault":false,"name":"百事+可口+红玫瑰礼盒","styleId":16,"type":"style"},{"index":17,"isDefault":false,"name":"百事+可口+大红玫瑰礼盒","styleId":17,"type":"style"}]},{"isDefault":false,"label":"尺码","list":[{"index":100,"isDefault":false,"name":"均码","sizeId":100,"type":"size"}]}],"sizeKey":"尺码","skus":[{"currency":"￥","img":"//s11.mogucdn.com/mlcdn/c45406/180803_35jdde4h21ld34df29073e53d25j9_800x800.jpg","nowprice":1380,"price":1972,"size":"均码","sizeId":100,"stock":952,"stockId":"116b9678","style":"可口可乐定制1罐","styleId":1,"xdSkuId":"116b9678"},{"currency":"￥","img":"//s3.mogucdn.com/mlcdn/c45406/180803_4b8503c2e51hi4ee1i0lfe44laaca_800x800.jpg","nowprice":1380,"price":1972,"size":"均码","sizeId":100,"stock":950,"stockId":"116b967a","style":"百事可乐定制1罐","styleId":2,"xdSkuId":"116b967a"},{"currency":"￥","img":"//s5.mogucdn.com/mlcdn/c45406/180803_3910730b2dlh4c1dc04i65c957gf1_800x800.jpg","nowprice":4900,"price":7000,"size":"均码","sizeId":100,"stock":980,"stockId":"116b967c","style":"可口可乐定制1罐+红玫瑰礼盒","styleId":3,"xdSkuId":"116b967c"},{"currency":"￥","img":"//s11.mogucdn.com/mlcdn/c45406/180803_236bj4b086l4k499f2e9lld94h04e_800x800.jpg","nowprice":4900,"price":7000,"size":"均码","sizeId":100,"stock":986,"stockId":"116b967e","style":"可口可乐定制1罐+蓝玫瑰礼盒","styleId":4,"xdSkuId":"116b967e"},{"currency":"￥","img":"//s3.mogucdn.com/mlcdn/c45406/180803_7g8j2f6ibb71bjad8i6lail9hl4ec_800x800.jpg","nowprice":4900,"price":7000,"size":"均码","sizeId":100,"stock":991,"stockId":"116b967g","style":"可口可乐定制1罐+粉玫瑰礼盒","styleId":5,"xdSkuId":"116b967g"},{"currency":"￥","img":"//s5.mogucdn.com/mlcdn/c45406/180803_55gikh12akakgj2jl8d2j437k1ck5_800x800.jpg","nowprice":4900,"price":7000,"size":"均码","sizeId":100,"stock":989,"stockId":"116b967i","style":"可口可乐定制1罐+浅紫色玫瑰礼盒","styleId":6,"xdSkuId":"116b967i"},{"currency":"￥","img":"//s3.mogucdn.com/mlcdn/c45406/180803_4a0772i0i992655112kgfb0i35k9d_800x800.jpg","nowprice":4900,"price":7000,"size":"均码","sizeId":100,"stock":993,"stockId":"116b967k","style":"可口可乐定制1罐+大红玫瑰礼盒","styleId":7,"xdSkuId":"116b967k"},{"currency":"￥","img":"//s3.mogucdn.com/mlcdn/c45406/180803_711f7843k08dl8idlhj3khf69i704_800x800.jpg","nowprice":4900,"price":7000,"size":"均码","sizeId":100,"stock":988,"stockId":"116b967m","style":"百事可乐定制1罐+红玫瑰礼盒","styleId":8,"xdSkuId":"116b967m"},{"currency":"￥","img":"//s5.mogucdn.com/mlcdn/c45406/180803_1jjac43808ja3j02415ffdeb55k32_800x800.jpg","nowprice":4900,"price":7000,"size":"均码","sizeId":100,"stock":989,"stockId":"116b967o","style":"百事可乐定制1罐+蓝玫瑰礼盒","styleId":9,"xdSkuId":"116b967o"},{"currency":"￥","img":"//s11.mogucdn.com/mlcdn/c45406/180803_314k9dcc8hgdg0a3ig945lcbejjff_800x800.jpg","nowprice":4900,"price":7000,"size":"均码","sizeId":100,"stock":992,"stockId":"116b967q","style":"百事可乐定制1罐+粉玫瑰礼盒","styleId":10,"xdSkuId":"116b967q"},{"currency":"￥","img":"//s11.mogucdn.com/mlcdn/c45406/180803_1e943bdk6h8b46759g88i29a5555e_800x800.jpg","nowprice":4900,"price":7000,"size":"均码","sizeId":100,"stock":997,"stockId":"116b967s","style":"百事可乐定制1罐+浅紫色玫瑰礼盒","styleId":11,"xdSkuId":"116b967s"},{"currency":"￥","img":"//s11.mogucdn.com/mlcdn/c45406/180803_8ef8k7e22f607cfaekg400kd20h1h_800x800.jpg","nowprice":4900,"price":7000,"size":"均码","sizeId":100,"stock":990,"stockId":"116b967u","style":"百事可乐定制1罐+大红玫瑰礼盒","styleId":12,"xdSkuId":"116b967u"},{"currency":"￥","img":"//s5.mogucdn.com/mlcdn/c45406/180803_3jd1eb508ki88f44882gd2gdai2lb_800x800.jpg","nowprice":5900,"price":8429,"size":"均码","sizeId":100,"stock":977,"stockId":"116b967w","style":"百事+可口+蓝玫瑰礼盒","styleId":13,"xdSkuId":"116b967w"},{"currency":"￥","img":"//s11.mogucdn.com/mlcdn/c45406/180803_6c90begl2e9db7e1j5kklkahgiaei_800x800.jpg","nowprice":5900,"price":8429,"size":"均码","sizeId":100,"stock":988,"stockId":"116b967y","style":"百事+可口+浅紫色玫瑰礼盒","styleId":14,"xdSkuId":"116b967y"},{"currency":"￥","img":"//s3.mogucdn.com/mlcdn/c45406/180803_15llb37jig4ichk447h7kg5j7ad76_800x800.jpg","nowprice":5900,"price":8429,"size":"均码","sizeId":100,"stock":997,"stockId":"116b9680","style":"百事+可口+粉玫瑰礼盒","styleId":15,"xdSkuId":"116b9680"},{"currency":"￥","img":"//s11.mogucdn.com/mlcdn/c45406/180803_5f0c2i4e7d8kglhb17cgc6gjdl440_800x800.jpg","nowprice":5900,"price":8429,"size":"均码","sizeId":100,"stock":975,"stockId":"116b9682","style":"百事+可口+红玫瑰礼盒","styleId":16,"xdSkuId":"116b9682"},{"currency":"￥","img":"//s3.mogucdn.com/mlcdn/c45406/180803_6f3jb94gg1349db48k25i7ihag6g6_800x800.jpg","nowprice":5900,"price":8429,"size":"均码","sizeId":100,"stock":981,"stockId":"116b9684","style":"百事+可口+大红玫瑰礼盒","styleId":17,"xdSkuId":"116b9684"}],"styleKey":"款式","title":"可乐定制易拉罐diy抖音热门同款生日礼物男女生毕业可口可乐礼盒","totalStock":16715},"topBar":{"img":"//s11.mogucdn.com/p1/150811/upload_ieytsmbrmm4wkm3ggizdambqmeyde_226x43.png","link":"http://www.xiaodian.com/h5/download"}},"status":{"code":1001,"msg":""}}